example/__init__.py
example/asgi.py
example/requirements.txt
example/settings.py
mote/.babelrc
mote/.editorconfig
mote/.eslintrc
mote/.nvmrc
mote/.stylelintrc
mote/__init__.py
mote/_config.json
mote/apps.py
mote/gulpfile.js
mote/models.py
mote/monkey.py
mote/monkey27.py
mote/monkey35.py
mote/package.json
mote/urls.py
mote/utils.py
mote/views.py
mote/webpack.config.js
mote/yarn.lock
mote/api/__init__.py
mote/build-helpers/webpack/helpers.js
mote/loaders/__init__.py
mote/loaders/app_directories.py
mote/loaders/cached.py
mote/mui-source/projects/mui/website/src/main.js
mote/mui-source/projects/mui/website/src/styles.scss
mote/mui-source/projects/mui/website/src/app/documentation-toggler.js
mote/mui-source/projects/mui/website/src/app/variation-toggler.js
mote/mui-source/projects/mui/website/src/app/helpers/document-ready.js
mote/mui-source/projects/mui/website/src/config/_config.scss
mote/mui-source/projects/mui/website/src/config/_pattern-presets.scss
mote/mui-source/projects/mui/website/src/patterns/atoms/color-swatch/_color-swatch.scss
mote/mui-source/projects/mui/website/src/patterns/atoms/color-swatch/color-swatch.html
mote/mui-source/projects/mui/website/src/patterns/atoms/color-swatch/index.html
mote/mui-source/projects/mui/website/src/patterns/atoms/content-area/_content-area.scss
mote/mui-source/projects/mui/website/src/patterns/atoms/content-area/index.html
mote/mui-source/projects/mui/website/src/patterns/atoms/logo/_logo.scss
mote/mui-source/projects/mui/website/src/patterns/atoms/logo/index.html
mote/mui-source/projects/mui/website/src/patterns/molecules/button-group/_button-group.scss
mote/mui-source/projects/mui/website/src/patterns/molecules/menu/_menu.scss
mote/mui-source/projects/mui/website/src/patterns/molecules/nav-grid/_nav-grid.scss
mote/mui-source/projects/mui/website/src/patterns/organisms/documentation/_documentation.scss
mote/mui-source/projects/mui/website/src/patterns/organisms/header/_header.scss
mote_praekelt-0.3.0.dist-info/AUTHORS.rst
mote_praekelt-0.3.0.dist-info/LICENSE
mote_praekelt-0.3.0.dist-info/METADATA
mote_praekelt-0.3.0.dist-info/WHEEL
mote_praekelt-0.3.0.dist-info/top_level.txt
mote_praekelt-0.3.0.dist-info/zip-safe
mote_praekelt-0.3.0.dist-info/RECORD
