Metadata-Version: 2.1
Name: mote-praekelt
Version: 0.3.0
Summary: Mote - the pattern library framework.
Home-page: https://github.com/praekelt/mote
Author: Praekelt Foundation
Author-email: dev@praekelt.org
License: BSD
Platform: UNKNOWN
Classifier: Framework :: Django
Classifier: Intended Audience :: Developers
Classifier: License :: OSI Approved :: BSD License
Classifier: Natural Language :: English
Classifier: Operating System :: OS Independent
Classifier: Programming Language :: Python
Classifier: Topic :: Internet :: WWW/HTTP :: Dynamic Content
Requires-Dist: django
Requires-Dist: beautifulsoup4
Requires-Dist: six
Requires-Dist: djangorestframework-jwt
Requires-Dist: djangorestframework
Requires-Dist: xmltodict
Requires-Dist: PyYAML
Requires-Dist: yamlordereddictloader
Requires-Dist: pypandoc
Requires-Dist: dill
